{
  "section_number": 14,
  "section_title": "Audio, Broadcasting, and Entertainment",
  "subsections": [
    {
      "name": "Professional Audio Systems",
      "keywords": [
        {
          "keyword": "Professional Audio PCB",
          "used": false,
          "template": null,
          "usage_date": null,
          "notes": "",
          "subsection": "Professional Audio Systems"
        },
        {
          "keyword": "Audio Console PCB",
          "used": false,
          "template": null,
          "usage_date": null,
          "notes": "",
          "subsection": "Professional Audio Systems"
        },
        {
          "keyword": "Mixing Console PCB",
          "used": false,
          "template": null,
          "usage_date": null,
          "notes": "",
          "subsection": "Professional Audio Systems"
        },
        {
          "keyword": "Digital Mixer PCB",
          "used": false,
          "template": null,
          "usage_date": null,
          "notes": "",
          "subsection": "Professional Audio Systems"
        },
        {
          "keyword": "Analog Mixer PCB",
          "used": false,
          "template": null,
          "usage_date": null,
          "notes": "",
          "subsection": "Professional Audio Systems"
        },
        {
          "keyword": "Audio Interface PCB",
          "used": false,
          "template": null,
          "usage_date": null,
          "notes": "",
          "subsection": "Professional Audio Systems"
        },
        {
          "keyword": "Recording Interface",
          "used": false,
          "template": null,
          "usage_date": null,
          "notes": "",
          "subsection": "Professional Audio Systems"
        },
        {
          "keyword": "Studio Interface PCB",
          "used": false,
          "template": null,
          "usage_date": null,
          "notes": "",
          "subsection": "Professional Audio Systems"
        },
        {
          "keyword": "Live Sound PCB",
          "used": false,
          "template": null,
          "usage_date": null,
          "notes": "",
          "subsection": "Professional Audio Systems"
        },
        {
          "keyword": "Concert Audio PCB",
          "used": false,
          "template": null,
          "usage_date": null,
          "notes": "",
          "subsection": "Professional Audio Systems"
        },
        {
          "keyword": "Theater Audio PCB",
          "used": false,
          "template": null,
          "usage_date": null,
          "notes": "",
          "subsection": "Professional Audio Systems"
        },
        {
          "keyword": "Church Audio PCB",
          "used": false,
          "template": null,
          "usage_date": null,
          "notes": "",
          "subsection": "Professional Audio Systems"
        },
        {
          "keyword": "Conference Audio PCB",
          "used": false,
          "template": null,
          "usage_date": null,
          "notes": "",
          "subsection": "Professional Audio Systems"
        },
        {
          "keyword": "Broadcast Audio PCB",
          "used": false,
          "template": null,
          "usage_date": null,
          "notes": "",
          "subsection": "Professional Audio Systems"
        },
        {
          "keyword": "Radio Studio PCB",
          "used": false,
          "template": null,
          "usage_date": null,
          "notes": "",
          "subsection": "Professional Audio Systems"
        },
        {
          "keyword": "TV Studio PCB",
          "used": false,
          "template": null,
          "usage_date": null,
          "notes": "",
          "subsection": "Professional Audio Systems"
        },
        {
          "keyword": "Post Production PCB",
          "used": false,
          "template": null,
          "usage_date": null,
          "notes": "",
          "subsection": "Professional Audio Systems"
        },
        {
          "keyword": "Mastering PCB",
          "used": false,
          "template": null,
          "usage_date": null,
          "notes": "",
          "subsection": "Professional Audio Systems"
        },
        {
          "keyword": "Audio Router PCB",
          "used": false,
          "template": null,
          "usage_date": null,
          "notes": "",
          "subsection": "Professional Audio Systems"
        },
        {
          "keyword": "Audio Matrix PCB",
          "used": false,
          "template": null,
          "usage_date": null,
          "notes": "",
          "subsection": "Professional Audio Systems"
        },
        {
          "keyword": "Audio Distribution",
          "used": false,
          "template": null,
          "usage_date": null,
          "notes": "",
          "subsection": "Professional Audio Systems"
        },
        {
          "keyword": "Digital Audio PCB",
          "used": false,
          "template": null,
          "usage_date": null,
          "notes": "",
          "subsection": "Professional Audio Systems"
        },
        {
          "keyword": "AES/EBU PCB",
          "used": false,
          "template": null,
          "usage_date": null,
          "notes": "",
          "subsection": "Professional Audio Systems"
        },
        {
          "keyword": "MADI PCB",
          "used": false,
          "template": null,
          "usage_date": null,
          "notes": "",
          "subsection": "Professional Audio Systems"
        },
        {
          "keyword": "Dante PCB",
          "used": false,
          "template": null,
          "usage_date": null,
          "notes": "",
          "subsection": "Professional Audio Systems"
        },
        {
          "keyword": "AVB PCB",
          "used": false,
          "template": null,
          "usage_date": null,
          "notes": "",
          "subsection": "Professional Audio Systems"
        },
        {
          "keyword": "AES67 PCB",
          "used": false,
          "template": null,
          "usage_date": null,
          "notes": "",
          "subsection": "Professional Audio Systems"
        },
        {
          "keyword": "Ravenna PCB",
          "used": false,
          "template": null,
          "usage_date": null,
          "notes": "",
          "subsection": "Professional Audio Systems"
        },
        {
          "keyword": "Livewire PCB",
          "used": false,
          "template": null,
          "usage_date": null,
          "notes": "",
          "subsection": "Professional Audio Systems"
        },
        {
          "keyword": "WheatNet PCB",
          "used": false,
          "template": null,
          "usage_date": null,
          "notes": "",
          "subsection": "Professional Audio Systems"
        },
        {
          "keyword": "Audio over IP",
          "used": false,
          "template": null,
          "usage_date": null,
          "notes": "",
          "subsection": "Professional Audio Systems"
        }
      ]
    },
    {
      "name": "Amplification and Speaker Systems",
      "keywords": [
        {
          "keyword": "Audio Amplifier PCB",
          "used": false,
          "template": null,
          "usage_date": null,
          "notes": "",
          "subsection": "Amplification and Speaker Systems"
        },
        {
          "keyword": "Power Amplifier PCB",
          "used": false,
          "template": null,
          "usage_date": null,
          "notes": "",
          "subsection": "Amplification and Speaker Systems"
        },
        {
          "keyword": "Integrated Amplifier",
          "used": false,
          "template": null,
          "usage_date": null,
          "notes": "",
          "subsection": "Amplification and Speaker Systems"
        },
        {
          "keyword": "Preamplifier PCB",
          "used": false,
          "template": null,
          "usage_date": null,
          "notes": "",
          "subsection": "Amplification and Speaker Systems"
        },
        {
          "keyword": "Phono Preamp PCB",
          "used": false,
          "template": null,
          "usage_date": null,
          "notes": "",
          "subsection": "Amplification and Speaker Systems"
        },
        {
          "keyword": "Headphone Amplifier",
          "used": false,
          "template": null,
          "usage_date": null,
          "notes": "",
          "subsection": "Amplification and Speaker Systems"
        },
        {
          "keyword": "Class A Amplifier PCB",
          "used": false,
          "template": null,
          "usage_date": null,
          "notes": "",
          "subsection": "Amplification and Speaker Systems"
        },
        {
          "keyword": "Class AB Amplifier PCB",
          "used": false,
          "template": null,
          "usage_date": null,
          "notes": "",
          "subsection": "Amplification and Speaker Systems"
        },
        {
          "keyword": "Class D Amplifier PCB",
          "used": false,
          "template": null,
          "usage_date": null,
          "notes": "",
          "subsection": "Amplification and Speaker Systems"
        },
        {
          "keyword": "Class H Amplifier PCB",
          "used": false,
          "template": null,
          "usage_date": null,
          "notes": "",
          "subsection": "Amplification and Speaker Systems"
        },
        {
          "keyword": "Tube Amplifier PCB",
          "used": false,
          "template": null,
          "usage_date": null,
          "notes": "",
          "subsection": "Amplification and Speaker Systems"
        },
        {
          "keyword": "Solid State PCB",
          "used": false,
          "template": null,
          "usage_date": null,
          "notes": "",
          "subsection": "Amplification and Speaker Systems"
        },
        {
          "keyword": "Hybrid Amplifier PCB",
          "used": false,
          "template": null,
          "usage_date": null,
          "notes": "",
          "subsection": "Amplification and Speaker Systems"
        },
        {
          "keyword": "Multi-Channel PCB",
          "used": false,
          "template": null,
          "usage_date": null,
          "notes": "",
          "subsection": "Amplification and Speaker Systems"
        },
        {
          "keyword": "Bridged Amplifier PCB",
          "used": false,
          "template": null,
          "usage_date": null,
          "notes": "",
          "subsection": "Amplification and Speaker Systems"
        },
        {
          "keyword": "Mono Block PCB",
          "used": false,
          "template": null,
          "usage_date": null,
          "notes": "",
          "subsection": "Amplification and Speaker Systems"
        },
        {
          "keyword": "Stereo Amplifier PCB",
          "used": false,
          "template": null,
          "usage_date": null,
          "notes": "",
          "subsection": "Amplification and Speaker Systems"
        },
        {
          "keyword": "Surround Amplifier PCB",
          "used": false,
          "template": null,
          "usage_date": null,
          "notes": "",
          "subsection": "Amplification and Speaker Systems"
        },
        {
          "keyword": "Subwoofer Amplifier",
          "used": false,
          "template": null,
          "usage_date": null,
          "notes": "",
          "subsection": "Amplification and Speaker Systems"
        },
        {
          "keyword": "Active Speaker PCB",
          "used": false,
          "template": null,
          "usage_date": null,
          "notes": "",
          "subsection": "Amplification and Speaker Systems"
        },
        {
          "keyword": "Passive Speaker PCB",
          "used": false,
          "template": null,
          "usage_date": null,
          "notes": "",
          "subsection": "Amplification and Speaker Systems"
        },
        {
          "keyword": "Studio Monitor PCB",
          "used": false,
          "template": null,
          "usage_date": null,
          "notes": "",
          "subsection": "Amplification and Speaker Systems"
        },
        {
          "keyword": "PA Speaker PCB",
          "used": false,
          "template": null,
          "usage_date": null,
          "notes": "",
          "subsection": "Amplification and Speaker Systems"
        },
        {
          "keyword": "Line Array PCB",
          "used": false,
          "template": null,
          "usage_date": null,
          "notes": "",
          "subsection": "Amplification and Speaker Systems"
        },
        {
          "keyword": "Point Source PCB",
          "used": false,
          "template": null,
          "usage_date": null,
          "notes": "",
          "subsection": "Amplification and Speaker Systems"
        },
        {
          "keyword": "Horn Loaded PCB",
          "used": false,
          "template": null,
          "usage_date": null,
          "notes": "",
          "subsection": "Amplification and Speaker Systems"
        },
        {
          "keyword": "Compression Driver PCB",
          "used": false,
          "template": null,
          "usage_date": null,
          "notes": "",
          "subsection": "Amplification and Speaker Systems"
        },
        {
          "keyword": "Woofer PCB",
          "used": false,
          "template": null,
          "usage_date": null,
          "notes": "",
          "subsection": "Amplification and Speaker Systems"
        },
        {
          "keyword": "Tweeter PCB",
          "used": false,
          "template": null,
          "usage_date": null,
          "notes": "",
          "subsection": "Amplification and Speaker Systems"
        }
      ]
    },
    {
      "name": "Broadcasting and Transmission",
      "keywords": [
        {
          "keyword": "Broadcast Transmitter PCB",
          "used": false,
          "template": null,
          "usage_date": null,
          "notes": "",
          "subsection": "Broadcasting and Transmission"
        },
        {
          "keyword": "FM Transmitter PCB",
          "used": false,
          "template": null,
          "usage_date": null,
          "notes": "",
          "subsection": "Broadcasting and Transmission"
        },
        {
          "keyword": "AM Transmitter PCB",
          "used": false,
          "template": null,
          "usage_date": null,
          "notes": "",
          "subsection": "Broadcasting and Transmission"
        },
        {
          "keyword": "TV Transmitter PCB",
          "used": false,
          "template": null,
          "usage_date": null,
          "notes": "",
          "subsection": "Broadcasting and Transmission"
        },
        {
          "keyword": "Digital Transmitter PCB",
          "used": false,
          "template": null,
          "usage_date": null,
          "notes": "",
          "subsection": "Broadcasting and Transmission"
        },
        {
          "keyword": "HD Radio PCB",
          "used": false,
          "template": null,
          "usage_date": null,
          "notes": "",
          "subsection": "Broadcasting and Transmission"
        },
        {
          "keyword": "DAB Transmitter PCB",
          "used": false,
          "template": null,
          "usage_date": null,
          "notes": "",
          "subsection": "Broadcasting and Transmission"
        },
        {
          "keyword": "DRM Transmitter PCB",
          "used": false,
          "template": null,
          "usage_date": null,
          "notes": "",
          "subsection": "Broadcasting and Transmission"
        },
        {
          "keyword": "DVB Transmitter PCB",
          "used": false,
          "template": null,
          "usage_date": null,
          "notes": "",
          "subsection": "Broadcasting and Transmission"
        },
        {
          "keyword": "ATSC Transmitter PCB",
          "used": false,
          "template": null,
          "usage_date": null,
          "notes": "",
          "subsection": "Broadcasting and Transmission"
        },
        {
          "keyword": "ISDB Transmitter PCB",
          "used": false,
          "template": null,
          "usage_date": null,
          "notes": "",
          "subsection": "Broadcasting and Transmission"
        },
        {
          "keyword": "Solid State Transmitter",
          "used": false,
          "template": null,
          "usage_date": null,
          "notes": "",
          "subsection": "Broadcasting and Transmission"
        },
        {
          "keyword": "Tube Transmitter PCB",
          "used": false,
          "template": null,
          "usage_date": null,
          "notes": "",
          "subsection": "Broadcasting and Transmission"
        },
        {
          "keyword": "RF Amplifier PCB",
          "used": false,
          "template": null,
          "usage_date": null,
          "notes": "",
          "subsection": "Broadcasting and Transmission"
        },
        {
          "keyword": "RF Combiner PCB",
          "used": false,
          "template": null,
          "usage_date": null,
          "notes": "",
          "subsection": "Broadcasting and Transmission"
        },
        {
          "keyword": "Antenna Tuner PCB",
          "used": false,
          "template": null,
          "usage_date": null,
          "notes": "",
          "subsection": "Broadcasting and Transmission"
        },
        {
          "keyword": "Dummy Load PCB",
          "used": false,
          "template": null,
          "usage_date": null,
          "notes": "",
          "subsection": "Broadcasting and Transmission"
        },
        {
          "keyword": "RF Switch PCB",
          "used": false,
          "template": null,
          "usage_date": null,
          "notes": "",
          "subsection": "Broadcasting and Transmission"
        },
        {
          "keyword": "Directional Coupler PCB",
          "used": false,
          "template": null,
          "usage_date": null,
          "notes": "",
          "subsection": "Broadcasting and Transmission"
        },
        {
          "keyword": "Power Meter PCB",
          "used": false,
          "template": null,
          "usage_date": null,
          "notes": "",
          "subsection": "Broadcasting and Transmission"
        },
        {
          "keyword": "SWR Meter PCB",
          "used": false,
          "template": null,
          "usage_date": null,
          "notes": "",
          "subsection": "Broadcasting and Transmission"
        },
        {
          "keyword": "Modulation Monitor PCB",
          "used": false,
          "template": null,
          "usage_date": null,
          "notes": "",
          "subsection": "Broadcasting and Transmission"
        },
        {
          "keyword": "Audio Processor PCB",
          "used": false,
          "template": null,
          "usage_date": null,
          "notes": "",
          "subsection": "Broadcasting and Transmission"
        },
        {
          "keyword": "STL Link PCB",
          "used": false,
          "template": null,
          "usage_date": null,
          "notes": "",
          "subsection": "Broadcasting and Transmission"
        },
        {
          "keyword": "Microwave Link PCB",
          "used": false,
          "template": null,
          "usage_date": null,
          "notes": "",
          "subsection": "Broadcasting and Transmission"
        },
        {
          "keyword": "Satellite Uplink PCB",
          "used": false,
          "template": null,
          "usage_date": null,
          "notes": "",
          "subsection": "Broadcasting and Transmission"
        },
        {
          "keyword": "IP Streaming PCB",
          "used": false,
          "template": null,
          "usage_date": null,
          "notes": "",
          "subsection": "Broadcasting and Transmission"
        },
        {
          "keyword": "Encoding PCB",
          "used": false,
          "template": null,
          "usage_date": null,
          "notes": "",
          "subsection": "Broadcasting and Transmission"
        },
        {
          "keyword": "Decoding PCB",
          "used": false,
          "template": null,
          "usage_date": null,
          "notes": "",
          "subsection": "Broadcasting and Transmission"
        },
        {
          "keyword": "Multiplexer PCB",
          "used": false,
          "template": null,
          "usage_date": null,
          "notes": "",
          "subsection": "Broadcasting and Transmission"
        }
      ]
    },
    {
      "name": "Content Creation and Post-Production",
      "keywords": [
        {
          "keyword": "Video Production PCB",
          "used": false,
          "template": null,
          "usage_date": null,
          "notes": "",
          "subsection": "Content Creation and Post-Production"
        },
        {
          "keyword": "Video Editor PCB",
          "used": false,
          "template": null,
          "usage_date": null,
          "notes": "",
          "subsection": "Content Creation and Post-Production"
        },
        {
          "keyword": "Video Switcher PCB",
          "used": false,
          "template": null,
          "usage_date": null,
          "notes": "",
          "subsection": "Content Creation and Post-Production"
        },
        {
          "keyword": "Vision Mixer PCB",
          "used": false,
          "template": null,
          "usage_date": null,
          "notes": "",
          "subsection": "Content Creation and Post-Production"
        },
        {
          "keyword": "Video Router PCB",
          "used": false,
          "template": null,
          "usage_date": null,
          "notes": "",
          "subsection": "Content Creation and Post-Production"
        },
        {
          "keyword": "Video Matrix PCB",
          "used": false,
          "template": null,
          "usage_date": null,
          "notes": "",
          "subsection": "Content Creation and Post-Production"
        },
        {
          "keyword": "Video Scaler PCB",
          "used": false,
          "template": null,
          "usage_date": null,
          "notes": "",
          "subsection": "Content Creation and Post-Production"
        },
        {
          "keyword": "Video Converter PCB",
          "used": false,
          "template": null,
          "usage_date": null,
          "notes": "",
          "subsection": "Content Creation and Post-Production"
        },
        {
          "keyword": "Frame Synchronizer PCB",
          "used": false,
          "template": null,
          "usage_date": null,
          "notes": "",
          "subsection": "Content Creation and Post-Production"
        },
        {
          "keyword": "Time Base Corrector",
          "used": false,
          "template": null,
          "usage_date": null,
          "notes": "",
          "subsection": "Content Creation and Post-Production"
        },
        {
          "keyword": "Color Corrector PCB",
          "used": false,
          "template": null,
          "usage_date": null,
          "notes": "",
          "subsection": "Content Creation and Post-Production"
        },
        {
          "keyword": "Video Processor PCB",
          "used": false,
          "template": null,
          "usage_date": null,
          "notes": "",
          "subsection": "Content Creation and Post-Production"
        },
        {
          "keyword": "Graphics Generator PCB",
          "used": false,
          "template": null,
          "usage_date": null,
          "notes": "",
          "subsection": "Content Creation and Post-Production"
        },
        {
          "keyword": "Character Generator PCB",
          "used": false,
          "template": null,
          "usage_date": null,
          "notes": "",
          "subsection": "Content Creation and Post-Production"
        },
        {
          "keyword": "Keyer PCB",
          "used": false,
          "template": null,
          "usage_date": null,
          "notes": "",
          "subsection": "Content Creation and Post-Production"
        },
        {
          "keyword": "DVE PCB",
          "used": false,
          "template": null,
          "usage_date": null,
          "notes": "",
          "subsection": "Content Creation and Post-Production"
        },
        {
          "keyword": "Video Server PCB",
          "used": false,
          "template": null,
          "usage_date": null,
          "notes": "",
          "subsection": "Content Creation and Post-Production"
        },
        {
          "keyword": "Playout Server PCB",
          "used": false,
          "template": null,
          "usage_date": null,
          "notes": "",
          "subsection": "Content Creation and Post-Production"
        },
        {
          "keyword": "Media Server PCB",
          "used": false,
          "template": null,
          "usage_date": null,
          "notes": "",
          "subsection": "Content Creation and Post-Production"
        },
        {
          "keyword": "Storage System PCB",
          "used": false,
          "template": null,
          "usage_date": null,
          "notes": "",
          "subsection": "Content Creation and Post-Production"
        },
        {
          "keyword": "SAN Storage PCB",
          "used": false,
          "template": null,
          "usage_date": null,
          "notes": "",
          "subsection": "Content Creation and Post-Production"
        },
        {
          "keyword": "NAS Storage PCB",
          "used": false,
          "template": null,
          "usage_date": null,
          "notes": "",
          "subsection": "Content Creation and Post-Production"
        },
        {
          "keyword": "Archive System PCB",
          "used": false,
          "template": null,
          "usage_date": null,
          "notes": "",
          "subsection": "Content Creation and Post-Production"
        },
        {
          "keyword": "Asset Management PCB",
          "used": false,
          "template": null,
          "usage_date": null,
          "notes": "",
          "subsection": "Content Creation and Post-Production"
        },
        {
          "keyword": "Workflow System PCB",
          "used": false,
          "template": null,
          "usage_date": null,
          "notes": "",
          "subsection": "Content Creation and Post-Production"
        },
        {
          "keyword": "Transcoding PCB",
          "used": false,
          "template": null,
          "usage_date": null,
          "notes": "",
          "subsection": "Content Creation and Post-Production"
        },
        {
          "keyword": "Compression PCB",
          "used": false,
          "template": null,
          "usage_date": null,
          "notes": "",
          "subsection": "Content Creation and Post-Production"
        },
        {
          "keyword": "Streaming PCB",
          "used": false,
          "template": null,
          "usage_date": null,
          "notes": "",
          "subsection": "Content Creation and Post-Production"
        },
        {
          "keyword": "CDN PCB",
          "used": false,
          "template": null,
          "usage_date": null,
          "notes": "",
          "subsection": "Content Creation and Post-Production"
        },
        {
          "keyword": "Delivery PCB",
          "used": false,
          "template": null,
          "usage_date": null,
          "notes": "",
          "subsection": "Content Creation and Post-Production"
        }
      ]
    },
    {
      "name": "Home Entertainment and Consumer Audio",
      "keywords": [
        {
          "keyword": "Home Theater PCB",
          "used": true,
          "template": "audio-entertainment-pcb-v3.md",
          "usage_date": "2025-09-27",
          "notes": "Generated by batch script",
          "subsection": "Home Entertainment and Consumer Audio"
        },
        {
          "keyword": "AV Receiver PCB",
          "used": false,
          "template": null,
          "usage_date": null,
          "notes": "",
          "subsection": "Home Entertainment and Consumer Audio"
        },
        {
          "keyword": "Surround Sound PCB",
          "used": true,
          "template": "audio-entertainment-pcb-v2.md",
          "usage_date": "2025-09-26",
          "notes": "Generated by batch script",
          "subsection": "Home Entertainment and Consumer Audio"
        },
        {
          "keyword": "Soundbar PCB",
          "used": false,
          "template": null,
          "usage_date": null,
          "notes": "",
          "subsection": "Home Entertainment and Consumer Audio"
        },
        {
          "keyword": "Subwoofer PCB",
          "used": false,
          "template": null,
          "usage_date": null,
          "notes": "",
          "subsection": "Home Entertainment and Consumer Audio"
        },
        {
          "keyword": "Media Player PCB",
          "used": true,
          "template": "audio-entertainment-pcb-v3.md",
          "usage_date": "2025-09-27",
          "notes": "Generated by batch script",
          "subsection": "Home Entertainment and Consumer Audio"
        },
        {
          "keyword": "Streaming Device PCB",
          "used": true,
          "template": "audio-entertainment-pcb-v3.md",
          "usage_date": "2025-09-27",
          "notes": "Generated by batch script",
          "subsection": "Home Entertainment and Consumer Audio"
        },
        {
          "keyword": "Set Top Box PCB",
          "used": false,
          "template": null,
          "usage_date": null,
          "notes": "",
          "subsection": "Home Entertainment and Consumer Audio"
        },
        {
          "keyword": "Cable Box PCB",
          "used": false,
          "template": null,
          "usage_date": null,
          "notes": "",
          "subsection": "Home Entertainment and Consumer Audio"
        },
        {
          "keyword": "Satellite Receiver",
          "used": false,
          "template": null,
          "usage_date": null,
          "notes": "",
          "subsection": "Home Entertainment and Consumer Audio"
        },
        {
          "keyword": "Blu-ray Player PCB",
          "used": false,
          "template": null,
          "usage_date": null,
          "notes": "",
          "subsection": "Home Entertainment and Consumer Audio"
        },
        {
          "keyword": "DVD Player PCB",
          "used": false,
          "template": null,
          "usage_date": null,
          "notes": "",
          "subsection": "Home Entertainment and Consumer Audio"
        },
        {
          "keyword": "Gaming Console PCB",
          "used": false,
          "template": null,
          "usage_date": null,
          "notes": "",
          "subsection": "Home Entertainment and Consumer Audio"
        },
        {
          "keyword": "Game Controller PCB",
          "used": false,
          "template": null,
          "usage_date": null,
          "notes": "",
          "subsection": "Home Entertainment and Consumer Audio"
        },
        {
          "keyword": "Remote Control PCB",
          "used": false,
          "template": null,
          "usage_date": null,
          "notes": "",
          "subsection": "Home Entertainment and Consumer Audio"
        },
        {
          "keyword": "Universal Remote PCB",
          "used": false,
          "template": null,
          "usage_date": null,
          "notes": "",
          "subsection": "Home Entertainment and Consumer Audio"
        },
        {
          "keyword": "HDMI Switch PCB",
          "used": false,
          "template": null,
          "usage_date": null,
          "notes": "",
          "subsection": "Home Entertainment and Consumer Audio"
        },
        {
          "keyword": "HDMI Splitter PCB",
          "used": false,
          "template": null,
          "usage_date": null,
          "notes": "",
          "subsection": "Home Entertainment and Consumer Audio"
        },
        {
          "keyword": "Audio Extractor PCB",
          "used": false,
          "template": null,
          "usage_date": null,
          "notes": "",
          "subsection": "Home Entertainment and Consumer Audio"
        },
        {
          "keyword": "Video Processor PCB",
          "used": false,
          "template": null,
          "usage_date": null,
          "notes": "",
          "subsection": "Home Entertainment and Consumer Audio"
        },
        {
          "keyword": "Display Controller",
          "used": false,
          "template": null,
          "usage_date": null,
          "notes": "",
          "subsection": "Home Entertainment and Consumer Audio"
        },
        {
          "keyword": "Entertainment Hub PCB",
          "used": false,
          "template": null,
          "usage_date": null,
          "notes": "",
          "subsection": "Home Entertainment and Consumer Audio"
        },
        {
          "keyword": "Smart TV PCB",
          "used": false,
          "template": null,
          "usage_date": null,
          "notes": "",
          "subsection": "Home Entertainment and Consumer Audio"
        },
        {
          "keyword": "Android TV PCB",
          "used": false,
          "template": null,
          "usage_date": null,
          "notes": "",
          "subsection": "Home Entertainment and Consumer Audio"
        },
        {
          "keyword": "Apple TV PCB",
          "used": true,
          "template": "audio-entertainment-pcb-v3.md",
          "usage_date": "2025-09-27",
          "notes": "Generated by batch script",
          "subsection": "Home Entertainment and Consumer Audio"
        },
        {
          "keyword": "Roku PCB",
          "used": false,
          "template": null,
          "usage_date": null,
          "notes": "",
          "subsection": "Home Entertainment and Consumer Audio"
        },
        {
          "keyword": "Fire TV PCB",
          "used": false,
          "template": null,
          "usage_date": null,
          "notes": "",
          "subsection": "Home Entertainment and Consumer Audio"
        },
        {
          "keyword": "Chromecast PCB",
          "used": true,
          "template": "audio-entertainment-pcb-v3.md",
          "usage_date": "2025-09-27",
          "notes": "Generated by batch script",
          "subsection": "Home Entertainment and Consumer Audio"
        },
        {
          "keyword": "Audio Streaming PCB",
          "used": true,
          "template": "audio-entertainment-pcb-v3.md",
          "usage_date": "2025-09-27",
          "notes": "Generated by batch script",
          "subsection": "Home Entertainment and Consumer Audio"
        },
        {
          "keyword": "Multi-Room Audio",
          "used": false,
          "template": null,
          "usage_date": null,
          "notes": "",
          "subsection": "Home Entertainment and Consumer Audio"
        }
      ]
    }
  ],
  "available_templates": [
    "audio-entertainment-pcb-v1.md",
    "audio-entertainment-pcb-v2.md",
    "audio-entertainment-pcb-v3.md"
  ],
  "template_usage_stats": {
    "audio-entertainment-pcb-v1.md": {
      "usage_count": 0,
      "last_used": null,
      "created_blogs": []
    },
    "audio-entertainment-pcb-v2.md": {
      "usage_count": 0,
      "last_used": null,
      "created_blogs": []
    },
    "audio-entertainment-pcb-v3.md": {
      "usage_count": 0,
      "last_used": null,
      "created_blogs": []
    }
  }
}